causal_ai/__init__.py
causal_ai-0.0.0.dist-info/WHEEL
causal_ai-0.0.0.dist-info/METADATA
causal_ai-0.0.0.dist-info/RECORD
